LICENSE
MANIFEST.in
README.md
setup.py
LintPlaybook.egg-info/PKG-INFO
LintPlaybook.egg-info/SOURCES.txt
LintPlaybook.egg-info/dependency_links.txt
LintPlaybook.egg-info/requires.txt
LintPlaybook.egg-info/top_level.txt
bin/lint-pbook
linter/__init__.py
linter/runner.py
linter/version.py
linter/rules/__init__.py
linter/rules/undefinedVar.py
linter/utils/__init__.py
linter/utils/composite_queue.py
sample_data/ansible.cfg
sample_data/hosts
sample_data/output.jpg
sample_data/playbook.yml
sample_data/group_vars/ips