Metadata-Version: 1.1
Name: LintPlaybook
Version: 0.1.dev1
Summary: Lint ansible-playbooks for logical pitfalls
Home-page: https://github.com/host-anshu/lint-playbook
Author: Anshu Choubey
Author-email: anshu.choubey@imaginea.com
License: MIT
Keywords: ansible ansible-playbook dry-run lint ansible-lint interceptor
Platform: UNKNOWN
Classifier: Development Status :: 3 - Alpha
Classifier: Intended Audience :: Developers
Classifier: Topic :: Software Development :: Libraries :: Python Modules
Classifier: License :: OSI Approved :: MIT License
Classifier: Programming Language :: Python :: 2
Classifier: Programming Language :: Python :: 2.6
Classifier: Programming Language :: Python :: 2.7
